{"versao":1,"geradoEm":"2026-04-23T19:39:27.862Z","roots":[{"nome":"Fluxo Caixa Operacional","tipo":"S","macro":"OPERACIONAL","codigo":"","children":[{"id":221,"nome":"RECEITAS OPERACIONAIS","tipo":"S","macro":"OPERACIONAL","codigo":"1.1","children":[{"id":2,"nome":"Receitas de vendas de produto","tipo":"A","macro":"OPERACIONAL","codigo":"1.1.1","children":[],"pathKey":"M0/0/0"},{"id":3,"nome":"Receitas de vendas de serviço","tipo":"A","macro":"OPERACIONAL","codigo":"1.1.2","children":[],"pathKey":"M0/0/1"}],"pathKey":"M0/0"},{"id":null,"nome":"DEVOLUÇÕES","tipo":"S","macro":"OPERACIONAL","codigo":"","children":[{"id":210,"nome":"Devolução de pagamento","tipo":"A","macro":"OPERACIONAL","codigo":"","children":[],"pathKey":"M0/1/0"},{"id":346,"nome":"Devolução fatura","tipo":"A","macro":"OPERACIONAL","codigo":"","children":[],"pathKey":"M0/1/1"},{"id":263,"nome":"Devoluções de vendas","tipo":"A","macro":"OPERACIONAL","codigo":"","children":[],"pathKey":"M0/1/2"}],"pathKey":"M0/1"},{"id":220,"nome":"RECEITAS NÃO OPERACIONAIS","tipo":"S","macro":"OPERACIONAL","codigo":"2.2","children":[{"id":120,"nome":"Aporte de investimento de sócios","tipo":"A","macro":"OPERACIONAL","codigo":"2.2.1","children":[],"pathKey":"M0/2/0"},{"id":121,"nome":"Pagamento de empréstimo de sócios","tipo":"A","macro":"OPERACIONAL","codigo":"2.2.2","children":[],"pathKey":"M0/2/1"},{"id":322,"nome":"Recebimentos de Títulos Recomprados","tipo":"A","macro":"OPERACIONAL","codigo":"2.2.25","children":[],"pathKey":"M0/2/2"},{"id":323,"nome":"Recompra de Título","tipo":"A","macro":"OPERACIONAL","codigo":"2.2.26","children":[],"pathKey":"M0/2/3"},{"id":324,"nome":"Captações de Empréstimos e Financiamentos","tipo":"A","macro":"OPERACIONAL","codigo":"2.2.28","children":[],"pathKey":"M0/2/4"},{"id":233,"nome":"Venda de Imobilizado","tipo":"A","macro":"OPERACIONAL","codigo":"2.2.3","children":[],"pathKey":"M0/2/5"},{"id":231,"nome":"Descontos obtidos","tipo":"A","macro":"OPERACIONAL","codigo":"2.2.30","children":[],"pathKey":"M0/2/6"},{"id":234,"nome":"Juros auferidos","tipo":"A","macro":"OPERACIONAL","codigo":"2.2.4","children":[],"pathKey":"M0/2/7"},{"id":306,"nome":"Outras receitas","tipo":"A","macro":"OPERACIONAL","codigo":"2.2.5","children":[],"pathKey":"M0/2/8"},{"id":241,"nome":"Outras recuperações","tipo":"A","macro":"OPERACIONAL","codigo":"2.2.6","children":[],"pathKey":"M0/2/9"},{"id":125,"nome":"Rendimento de aplicações financeiras","tipo":"A","macro":"OPERACIONAL","codigo":"2.2.7","children":[],"pathKey":"M0/2/10"},{"id":166,"nome":"Transf entre empresas do grupo - Crédito","tipo":"A","macro":"OPERACIONAL","codigo":"2.2.9","children":[],"pathKey":"M0/2/11"}],"pathKey":"M0/2"},{"id":223,"nome":"CUSTO","tipo":"S","macro":"OPERACIONAL","codigo":"3","children":[{"id":230,"nome":"CMV","tipo":"S","macro":"OPERACIONAL","codigo":"3.1","children":[{"id":149,"nome":"Fornecedor - Material revenda","tipo":"A","macro":"OPERACIONAL","codigo":"3.1.1","children":[],"pathKey":"M0/3/0/0"}],"pathKey":"M0/3/0"},{"id":232,"nome":"CPV","tipo":"S","macro":"OPERACIONAL","codigo":"3.2","children":[{"id":25,"nome":"Fornecedor - Materia Prima","tipo":"A","macro":"OPERACIONAL","codigo":"3.2.1","children":[],"pathKey":"M0/3/1/0"},{"id":26,"nome":"Fornecedor - Material Embalagem","tipo":"A","macro":"OPERACIONAL","codigo":"3.2.2","children":[],"pathKey":"M0/3/1/1"},{"id":253,"nome":"Fornecedor - Material Insumos","tipo":"A","macro":"OPERACIONAL","codigo":"3.2.3","children":[],"pathKey":"M0/3/1/2"},{"id":254,"nome":"Prestador de serviços - Custo","tipo":"A","macro":"OPERACIONAL","codigo":"3.2.4","children":[],"pathKey":"M0/3/1/3"},{"id":370,"nome":"Serviços Terceirizados de Produção","tipo":"S","macro":"OPERACIONAL","codigo":"","children":[{"id":370,"nome":"Serviços Terceirizados de Produção","tipo":"A","macro":"OPERACIONAL","codigo":"3.2.5","children":[],"pathKey":"M0/3/1/4/0"},{"id":365,"nome":"Alugueis de Equipamentos Produção","tipo":"A","macro":"OPERACIONAL","codigo":"","children":[],"pathKey":"M0/3/1/4/1"},{"id":342,"nome":"Análises e Inspeções Técnicas","tipo":"A","macro":"OPERACIONAL","codigo":"","children":[],"pathKey":"M0/3/1/4/2"},{"id":154,"nome":"Laboratorio, analises e pesquisas","tipo":"A","macro":"OPERACIONAL","codigo":"","children":[],"pathKey":"M0/3/1/4/3"},{"id":304,"nome":"Energia Elétrica","tipo":"S","macro":"OPERACIONAL","codigo":"","children":[{"id":304,"nome":"Energia elétrica","tipo":"A","macro":"OPERACIONAL","codigo":"","children":[],"pathKey":"M0/3/1/4/4/0"},{"id":null,"nome":"Movimentação e Armazenagem","tipo":"S","macro":"OPERACIONAL","codigo":"","children":[{"id":276,"nome":"Fretes e carretos","tipo":"A","macro":"OPERACIONAL","codigo":"","children":[],"pathKey":"M0/3/1/4/4/1/0"},{"id":235,"nome":"CPV/CMV","tipo":"S","macro":"OPERACIONAL","codigo":"3.3","children":[{"id":24,"nome":"Fretes - Mercadorias","tipo":"A","macro":"OPERACIONAL","codigo":"3.3.1","children":[],"pathKey":"M0/3/1/4/4/1/1/0"}],"pathKey":"M0/3/1/4/4/1/1"}],"pathKey":"M0/3/1/4/4/1"}],"pathKey":"M0/3/1/4/4"}],"pathKey":"M0/3/1/4"}],"pathKey":"M0/3/1"}],"pathKey":"M0/3"},{"id":null,"nome":"Despesas com Pessoal","tipo":"S","macro":"OPERACIONAL","codigo":"","children":[{"id":null,"nome":"Gastos com Pessoal Operação","tipo":"S","macro":"OPERACIONAL","codigo":"","children":[{"id":null,"nome":"Folha de Pagamento","tipo":"A","macro":"OPERACIONAL","codigo":"","children":[],"pathKey":"M0/4/0/0"},{"id":336,"nome":"Salários operacional","tipo":"A","macro":"OPERACIONAL","codigo":"","children":[],"pathKey":"M0/4/0/1"},{"id":null,"nome":"INSS Operação","tipo":"A","macro":"OPERACIONAL","codigo":"","children":[],"pathKey":"M0/4/0/2"},{"id":null,"nome":"FGTS Operação","tipo":"A","macro":"OPERACIONAL","codigo":"","children":[],"pathKey":"M0/4/0/3"},{"id":180,"nome":"Horas Extras","tipo":"A","macro":"OPERACIONAL","codigo":"","children":[],"pathKey":"M0/4/0/4"},{"id":357,"nome":"Alimentação hora extra","tipo":"A","macro":"OPERACIONAL","codigo":"","children":[],"pathKey":"M0/4/0/5"},{"id":372,"nome":"Bonificação Operacional","tipo":"A","macro":"OPERACIONAL","codigo":"","children":[],"pathKey":"M0/4/0/6"},{"id":353,"nome":"Vale Transporte - Operacional","tipo":"A","macro":"OPERACIONAL","codigo":"","children":[],"pathKey":"M0/4/0/7"},{"id":354,"nome":"Vale Alimentacao/Refeição - Operacional","tipo":"A","macro":"OPERACIONAL","codigo":"","children":[],"pathKey":"M0/4/0/8"},{"id":171,"nome":"Pensão Alimentícia","tipo":"A","macro":"OPERACIONAL","codigo":"","children":[],"pathKey":"M0/4/0/9"},{"id":194,"nome":"Ajuda de Custo","tipo":"A","macro":"OPERACIONAL","codigo":"","children":[],"pathKey":"M0/4/0/10"}],"pathKey":"M0/4/0"},{"id":null,"nome":"Demais Gastos com Pessoal","tipo":"S","macro":"OPERACIONAL","codigo":"","children":[{"id":307,"nome":"Saude ocupacional","tipo":"A","macro":"OPERACIONAL","codigo":"","children":[],"pathKey":"M0/4/1/0"},{"id":385,"nome":"Auxílio Combustível - Operação","tipo":"A","macro":"OPERACIONAL","codigo":"","children":[],"pathKey":"M0/4/1/1"},{"id":49,"nome":"Seguro de vida","tipo":"A","macro":"OPERACIONAL","codigo":"","children":[],"pathKey":"M0/4/1/2"},{"id":301,"nome":"Contribuição sindical","tipo":"A","macro":"OPERACIONAL","codigo":"","children":[],"pathKey":"M0/4/1/3"}],"pathKey":"M0/4/1"},{"id":null,"nome":"Desenvolvimento de Colaboradores","tipo":"S","macro":"OPERACIONAL","codigo":"","children":[{"id":67,"nome":"Treinamentos e Certificações","tipo":"A","macro":"OPERACIONAL","codigo":"","children":[],"pathKey":"M0/4/2/0"}],"pathKey":"M0/4/2"},{"id":null,"nome":"EPI e Uniformes","tipo":"S","macro":"OPERACIONAL","codigo":"","children":[{"id":93,"nome":"EPI","tipo":"A","macro":"OPERACIONAL","codigo":"","children":[],"pathKey":"M0/4/3/0"},{"id":92,"nome":"Fardamento","tipo":"A","macro":"OPERACIONAL","codigo":"","children":[],"pathKey":"M0/4/3/1"}],"pathKey":"M0/4/3"},{"id":null,"nome":"Gastos com Pessoal Logística","tipo":"S","macro":"OPERACIONAL","codigo":"","children":[{"id":337,"nome":"Salários Logística","tipo":"A","macro":"OPERACIONAL","codigo":"","children":[],"pathKey":"M0/4/4/0"},{"id":null,"nome":"13º Salário - Logística","tipo":"A","macro":"OPERACIONAL","codigo":"","children":[],"pathKey":"M0/4/4/1"},{"id":null,"nome":"Provisão FGTS Fperias","tipo":"A","macro":"OPERACIONAL","codigo":"","children":[],"pathKey":"M0/4/4/2"},{"id":null,"nome":"INSS Logística","tipo":"A","macro":"OPERACIONAL","codigo":"","children":[],"pathKey":"M0/4/4/3"},{"id":null,"nome":"FGTS Logística","tipo":"A","macro":"OPERACIONAL","codigo":"","children":[],"pathKey":"M0/4/4/4"},{"id":386,"nome":"Auxílio Combustível - Logística","tipo":"A","macro":"OPERACIONAL","codigo":"","children":[],"pathKey":"M0/4/4/5"}],"pathKey":"M0/4/4"},{"id":null,"nome":"Gastos com Pessoal Administrativo","tipo":"S","macro":"OPERACIONAL","codigo":"","children":[{"id":null,"nome":"Folha de Pagamento","tipo":"A","macro":"OPERACIONAL","codigo":"","children":[],"pathKey":"M0/4/5/0"},{"id":37,"nome":"Salários","tipo":"A","macro":"OPERACIONAL","codigo":"","children":[],"pathKey":"M0/4/5/1"},{"id":189,"nome":"Adiantamentos a Colaboradores","tipo":"A","macro":"OPERACIONAL","codigo":"","children":[],"pathKey":"M0/4/5/2"},{"id":374,"nome":"Horas Extras - Administrativo","tipo":"A","macro":"OPERACIONAL","codigo":"","children":[],"pathKey":"M0/4/5/3"},{"id":376,"nome":"Vale transporte - Administrativo","tipo":"A","macro":"OPERACIONAL","codigo":"","children":[],"pathKey":"M0/4/5/4"},{"id":null,"nome":"13º Salários","tipo":"A","macro":"OPERACIONAL","codigo":"","children":[],"pathKey":"M0/4/5/5"},{"id":null,"nome":"INSS Administrativo","tipo":"A","macro":"OPERACIONAL","codigo":"","children":[],"pathKey":"M0/4/5/6"},{"id":null,"nome":"FGTS Administrativo","tipo":"A","macro":"OPERACIONAL","codigo":"","children":[],"pathKey":"M0/4/5/7"},{"id":null,"nome":"Provisão Férias","tipo":"A","macro":"OPERACIONAL","codigo":"","children":[],"pathKey":"M0/4/5/8"},{"id":null,"nome":"Provisão 1/3 Férias","tipo":"A","macro":"OPERACIONAL","codigo":"","children":[],"pathKey":"M0/4/5/9"},{"id":null,"nome":"Provisão INSS Férias","tipo":"A","macro":"OPERACIONAL","codigo":"","children":[],"pathKey":"M0/4/5/10"},{"id":null,"nome":"Provisão FGTS Férias","tipo":"A","macro":"OPERACIONAL","codigo":"","children":[],"pathKey":"M0/4/5/11"},{"id":53,"nome":"Pro-labore","tipo":"A","macro":"OPERACIONAL","codigo":"","children":[],"pathKey":"M0/4/5/12"}],"pathKey":"M0/4/5"},{"id":null,"nome":"Despesa Variáveis com Pessoal","tipo":"S","macro":"OPERACIONAL","codigo":"","children":[{"id":48,"nome":"Assist.Medica/Odontológica/Farmácia","tipo":"A","macro":"OPERACIONAL","codigo":"","children":[],"pathKey":"M0/4/6/0"},{"id":52,"nome":"Bolsa de estágio","tipo":"A","macro":"OPERACIONAL","codigo":"","children":[],"pathKey":"M0/4/6/1"},{"id":384,"nome":"Auxílio Combustível - Administrativo","tipo":"A","macro":"OPERACIONAL","codigo":"","children":[],"pathKey":"M0/4/6/2"},{"id":375,"nome":"Vale Alimentacao/Refeição - Administrativo","tipo":"A","macro":"OPERACIONAL","codigo":"","children":[],"pathKey":"M0/4/6/3"},{"id":356,"nome":"Refeições Corporativas","tipo":"A","macro":"OPERACIONAL","codigo":"","children":[],"pathKey":"M0/4/6/4"},{"id":327,"nome":"Bonificação - Administrativo","tipo":"A","macro":"OPERACIONAL","codigo":"","children":[],"pathKey":"M0/4/6/5"},{"id":302,"nome":"Despesas de Viagens","tipo":"A","macro":"OPERACIONAL","codigo":"","children":[],"pathKey":"M0/4/6/6"},{"id":null,"nome":"Treinamento e desenvolvimento","tipo":"A","macro":"OPERACIONAL","codigo":"","children":[],"pathKey":"M0/4/6/7"},{"id":373,"nome":"Fardamento Administrativo","tipo":"A","macro":"OPERACIONAL","codigo":"","children":[],"pathKey":"M0/4/6/8"}],"pathKey":"M0/4/6"},{"id":null,"nome":"Indenizações e Rescisões","tipo":"S","macro":"OPERACIONAL","codigo":"","children":[{"id":41,"nome":"FGTS multa rescisoria","tipo":"A","macro":"OPERACIONAL","codigo":"","children":[],"pathKey":"M0/4/7/0"},{"id":260,"nome":"Indenizações","tipo":"A","macro":"OPERACIONAL","codigo":"","children":[],"pathKey":"M0/4/7/1"},{"id":40,"nome":"Rescisões Trabalhistas","tipo":"A","macro":"OPERACIONAL","codigo":"","children":[],"pathKey":"M0/4/7/2"},{"id":294,"nome":"Dívida Trabalhista","tipo":"A","macro":"OPERACIONAL","codigo":"","children":[],"pathKey":"M0/4/7/3"}],"pathKey":"M0/4/7"}],"pathKey":"M0/4"},{"id":240,"nome":"Despesas Tributárias","tipo":"S","macro":"OPERACIONAL","codigo":"","children":[{"id":null,"nome":"Impostos sob Vendas","tipo":"S","macro":"OPERACIONAL","codigo":"","children":[{"id":8,"nome":"ICMS s/vendas","tipo":"A","macro":"OPERACIONAL","codigo":"","children":[],"pathKey":"M0/5/0/0"},{"id":350,"nome":"ICMS Difal","tipo":"A","macro":"OPERACIONAL","codigo":"","children":[],"pathKey":"M0/5/0/1"},{"id":137,"nome":"Icms substituição tributária","tipo":"A","macro":"OPERACIONAL","codigo":"","children":[],"pathKey":"M0/5/0/2"},{"id":310,"nome":"Icms Antecipado","tipo":"A","macro":"OPERACIONAL","codigo":"","children":[],"pathKey":"M0/5/0/3"},{"id":351,"nome":"ICMS Ativo Imobilizado","tipo":"A","macro":"OPERACIONAL","codigo":"","children":[],"pathKey":"M0/5/0/4"},{"id":381,"nome":"ICMS Difal Uso e Consumo","tipo":"A","macro":"OPERACIONAL","codigo":"","children":[],"pathKey":"M0/5/0/5"},{"id":7,"nome":"Cofins s/vendas","tipo":"A","macro":"OPERACIONAL","codigo":"","children":[],"pathKey":"M0/5/0/6"},{"id":null,"nome":"ISS","tipo":"A","macro":"OPERACIONAL","codigo":"","children":[],"pathKey":"M0/5/0/7"},{"id":6,"nome":"Pis s/vendas","tipo":"A","macro":"OPERACIONAL","codigo":"","children":[],"pathKey":"M0/5/0/8"},{"id":349,"nome":"Cotac","tipo":"A","macro":"OPERACIONAL","codigo":"","children":[],"pathKey":"M0/5/0/9"},{"id":348,"nome":"Funef","tipo":"A","macro":"OPERACIONAL","codigo":"","children":[],"pathKey":"M0/5/0/10"},{"id":382,"nome":"Fecop","tipo":"A","macro":"OPERACIONAL","codigo":"","children":[],"pathKey":"M0/5/0/11"},{"id":13,"nome":"Imposto - Simples Nacional","tipo":"A","macro":"OPERACIONAL","codigo":"","children":[],"pathKey":"M0/5/0/12"},{"id":null,"nome":"Impostos Produção","tipo":"A","macro":"OPERACIONAL","codigo":"","children":[],"pathKey":"M0/5/0/13"},{"id":9,"nome":"Ipi S/vendas","tipo":"A","macro":"OPERACIONAL","codigo":"","children":[],"pathKey":"M0/5/0/14"}],"pathKey":"M0/5/0"},{"id":null,"nome":"Impostos Sob o Lucro","tipo":"S","macro":"OPERACIONAL","codigo":"","children":[{"id":12,"nome":"CSLL","tipo":"A","macro":"OPERACIONAL","codigo":"","children":[],"pathKey":"M0/5/1/0"},{"id":11,"nome":"IRPJ","tipo":"A","macro":"OPERACIONAL","codigo":"","children":[],"pathKey":"M0/5/1/1"},{"id":44,"nome":"IRRF","tipo":"A","macro":"OPERACIONAL","codigo":"","children":[],"pathKey":"M0/5/1/2"}],"pathKey":"M0/5/1"}],"pathKey":"M0/5"},{"id":null,"nome":"Despesas Operacionais Indiretas","tipo":"S","macro":"OPERACIONAL","codigo":"","children":[{"id":null,"nome":"Serviços de Manutenção","tipo":"S","macro":"OPERACIONAL","codigo":"","children":[{"id":null,"nome":"Mecânica, Manutenção e Equipamentos","tipo":"A","macro":"OPERACIONAL","codigo":"","children":[],"pathKey":"M0/6/0/0"},{"id":null,"nome":"Manutenção Industrial","tipo":"A","macro":"OPERACIONAL","codigo":"","children":[],"pathKey":"M0/6/0/1"},{"id":389,"nome":"Serviços de Manutenção Industrial","tipo":"A","macro":"OPERACIONAL","codigo":"","children":[],"pathKey":"M0/6/0/2"},{"id":390,"nome":"Materiais de Manutenção Industrial","tipo":"A","macro":"OPERACIONAL","codigo":"","children":[],"pathKey":"M0/6/0/3"},{"id":111,"nome":"Materiais manutenção Mecanica","tipo":"A","macro":"OPERACIONAL","codigo":"","children":[],"pathKey":"M0/6/0/4"},{"id":270,"nome":"Serviços manutenção Mecanica","tipo":"A","macro":"OPERACIONAL","codigo":"","children":[],"pathKey":"M0/6/0/5"},{"id":272,"nome":"Materiais manutenção Eletrico","tipo":"A","macro":"OPERACIONAL","codigo":"","children":[],"pathKey":"M0/6/0/6"},{"id":102,"nome":"Materiais manutenção Hidraulico","tipo":"A","macro":"OPERACIONAL","codigo":"","children":[],"pathKey":"M0/6/0/7"},{"id":104,"nome":"Calibração de instrumentos","tipo":"A","macro":"OPERACIONAL","codigo":"","children":[],"pathKey":"M0/6/0/8"},{"id":352,"nome":"Peças, Ferramentas, Pneus","tipo":"A","macro":"OPERACIONAL","codigo":"","children":[],"pathKey":"M0/6/0/9"}],"pathKey":"M0/6/0"}],"pathKey":"M0/6"},{"id":null,"nome":"Despesas Logísticas","tipo":"S","macro":"OPERACIONAL","codigo":"","children":[{"id":328,"nome":"Despesas de Viagens OP","tipo":"A","macro":"OPERACIONAL","codigo":"","children":[],"pathKey":"M0/7/0"},{"id":null,"nome":"Despesas com Frota","tipo":"A","macro":"OPERACIONAL","codigo":"","children":[],"pathKey":"M0/7/1"},{"id":311,"nome":"IPVA E Licenciamentos","tipo":"A","macro":"OPERACIONAL","codigo":"","children":[],"pathKey":"M0/7/2"},{"id":74,"nome":"Combustíveis e Lubrificantes","tipo":"A","macro":"OPERACIONAL","codigo":"","children":[],"pathKey":"M0/7/3"},{"id":79,"nome":"Multas de Trânsito","tipo":"A","macro":"OPERACIONAL","codigo":"","children":[],"pathKey":"M0/7/4"},{"id":361,"nome":"Rastreamento de Veículos","tipo":"A","macro":"OPERACIONAL","codigo":"","children":[],"pathKey":"M0/7/5"},{"id":null,"nome":"Manutenção Veicular","tipo":"A","macro":"OPERACIONAL","codigo":"","children":[],"pathKey":"M0/7/6"},{"id":274,"nome":"Serviços manutenção de veiculos","tipo":"A","macro":"OPERACIONAL","codigo":"","children":[],"pathKey":"M0/7/7"},{"id":75,"nome":"Materiais de manut. de veículos","tipo":"A","macro":"OPERACIONAL","codigo":"","children":[],"pathKey":"M0/7/8"}],"pathKey":"M0/7"},{"id":null,"nome":"Despesas Administrativas","tipo":"S","macro":"OPERACIONAL","codigo":"","children":[{"id":null,"nome":"Despesas Prediais","tipo":"S","macro":"OPERACIONAL","codigo":"","children":[{"id":58,"nome":"Alugueis","tipo":"A","macro":"OPERACIONAL","codigo":"","children":[],"pathKey":"M0/8/0/0"},{"id":300,"nome":"IPTU e Condomínio","tipo":"A","macro":"OPERACIONAL","codigo":"","children":[],"pathKey":"M0/8/0/1"},{"id":69,"nome":"Segurança e Vigilância","tipo":"A","macro":"OPERACIONAL","codigo":"","children":[],"pathKey":"M0/8/0/2"},{"id":61,"nome":"Água e tratamento de efluentes","tipo":"A","macro":"OPERACIONAL","codigo":"","children":[],"pathKey":"M0/8/0/3"},{"id":273,"nome":"Materiais manutenção Predial","tipo":"A","macro":"OPERACIONAL","codigo":"","children":[],"pathKey":"M0/8/0/4"},{"id":271,"nome":"Serviços manutenção Predial","tipo":"A","macro":"OPERACIONAL","codigo":"","children":[],"pathKey":"M0/8/0/5"}],"pathKey":"M0/8/0"},{"id":null,"nome":"Endomarketing","tipo":"S","macro":"OPERACIONAL","codigo":"","children":[{"id":369,"nome":"Alimentação para Eventos","tipo":"A","macro":"OPERACIONAL","codigo":"","children":[],"pathKey":"M0/8/1/0"},{"id":364,"nome":"Serviços para Eventos","tipo":"A","macro":"OPERACIONAL","codigo":"","children":[],"pathKey":"M0/8/1/1"},{"id":368,"nome":"Materiais para Eventos","tipo":"A","macro":"OPERACIONAL","codigo":"","children":[],"pathKey":"M0/8/1/2"}],"pathKey":"M0/8/1"},{"id":null,"nome":"Despesas Burocráticas","tipo":"S","macro":"OPERACIONAL","codigo":"","children":[{"id":96,"nome":"Correios e Malotes","tipo":"A","macro":"OPERACIONAL","codigo":"","children":[],"pathKey":"M0/8/2/0"},{"id":341,"nome":"Cartórios","tipo":"A","macro":"OPERACIONAL","codigo":"","children":[],"pathKey":"M0/8/2/1"},{"id":317,"nome":"Taxas de Legalização","tipo":"A","macro":"OPERACIONAL","codigo":"","children":[],"pathKey":"M0/8/2/2"},{"id":343,"nome":"Multas Judiciais","tipo":"A","macro":"OPERACIONAL","codigo":"","children":[],"pathKey":"M0/8/2/3"},{"id":366,"nome":"Despachantes","tipo":"A","macro":"OPERACIONAL","codigo":"","children":[],"pathKey":"M0/8/2/4"},{"id":258,"nome":"Laudos ambientais","tipo":"A","macro":"OPERACIONAL","codigo":"","children":[],"pathKey":"M0/8/2/5"}],"pathKey":"M0/8/2"},{"id":302,"nome":"Despesas de Viagens","tipo":"S","macro":"OPERACIONAL","codigo":"","children":[{"id":84,"nome":"Passagens aereas","tipo":"A","macro":"OPERACIONAL","codigo":"","children":[],"pathKey":"M0/8/3/0"},{"id":86,"nome":"Evento clientes externos","tipo":"A","macro":"OPERACIONAL","codigo":"","children":[],"pathKey":"M0/8/3/1"},{"id":95,"nome":"Translados","tipo":"A","macro":"OPERACIONAL","codigo":"","children":[],"pathKey":"M0/8/3/2"},{"id":null,"nome":"Outras despesas de viagens","tipo":"A","macro":"OPERACIONAL","codigo":"","children":[],"pathKey":"M0/8/3/3"},{"id":null,"nome":"Taxi","tipo":"A","macro":"OPERACIONAL","codigo":"","children":[],"pathKey":"M0/8/3/4"},{"id":268,"nome":"Hospedagem","tipo":"A","macro":"OPERACIONAL","codigo":"","children":[],"pathKey":"M0/8/3/5"}],"pathKey":"M0/8/3"},{"id":null,"nome":"Despesas de Escritório","tipo":"S","macro":"OPERACIONAL","codigo":"","children":[{"id":89,"nome":"Material de escritório","tipo":"A","macro":"OPERACIONAL","codigo":"","children":[],"pathKey":"M0/8/4/0"},{"id":313,"nome":"Materiais de suprimentos de informatica","tipo":"A","macro":"OPERACIONAL","codigo":"","children":[],"pathKey":"M0/8/4/1"},{"id":null,"nome":"Manutenção de Infra","tipo":"A","macro":"OPERACIONAL","codigo":"","children":[],"pathKey":"M0/8/4/2"},{"id":362,"nome":"Despesas Gráficas","tipo":"A","macro":"OPERACIONAL","codigo":"","children":[],"pathKey":"M0/8/4/3"},{"id":363,"nome":"Despesas Holding","tipo":"A","macro":"OPERACIONAL","codigo":"","children":[],"pathKey":"M0/8/4/4"},{"id":280,"nome":"Alugueis de Equipamentos","tipo":"A","macro":"OPERACIONAL","codigo":"","children":[],"pathKey":"M0/8/4/5"}],"pathKey":"M0/8/4"},{"id":null,"nome":"Linhas/Redes","tipo":"S","macro":"OPERACIONAL","codigo":"","children":[{"id":367,"nome":"Internet","tipo":"A","macro":"OPERACIONAL","codigo":"","children":[],"pathKey":"M0/8/5/0"},{"id":55,"nome":"Telefonia celular","tipo":"A","macro":"OPERACIONAL","codigo":"","children":[],"pathKey":"M0/8/5/1"},{"id":285,"nome":"Telefonia fixa","tipo":"A","macro":"OPERACIONAL","codigo":"","children":[],"pathKey":"M0/8/5/2"}],"pathKey":"M0/8/5"},{"id":null,"nome":"Copas e Gerais","tipo":"S","macro":"OPERACIONAL","codigo":"","children":[{"id":358,"nome":"Higienização e Detetização","tipo":"A","macro":"OPERACIONAL","codigo":"","children":[],"pathKey":"M0/8/6/0"},{"id":90,"nome":"Material de Limpeza","tipo":"A","macro":"OPERACIONAL","codigo":"","children":[],"pathKey":"M0/8/6/1"},{"id":281,"nome":"Copa e Cozinha","tipo":"A","macro":"OPERACIONAL","codigo":"","children":[],"pathKey":"M0/8/6/2"}],"pathKey":"M0/8/6"},{"id":null,"nome":"Softwares","tipo":"S","macro":"OPERACIONAL","codigo":"","children":[{"id":62,"nome":"Manutenção licença de software","tipo":"A","macro":"OPERACIONAL","codigo":"","children":[],"pathKey":"M0/8/7/0"},{"id":326,"nome":"Software Gestão","tipo":"A","macro":"OPERACIONAL","codigo":"","children":[],"pathKey":"M0/8/7/1"}],"pathKey":"M0/8/7"},{"id":null,"nome":"Demais","tipo":"S","macro":"OPERACIONAL","codigo":"","children":[{"id":278,"nome":"Programa de Formação Profissional","tipo":"A","macro":"OPERACIONAL","codigo":"","children":[],"pathKey":"M0/8/8/0"},{"id":77,"nome":"Seguros","tipo":"A","macro":"OPERACIONAL","codigo":"","children":[],"pathKey":"M0/8/8/1"},{"id":345,"nome":"Gastos com Animais","tipo":"A","macro":"OPERACIONAL","codigo":"","children":[],"pathKey":"M0/8/8/2"}],"pathKey":"M0/8/8"},{"id":null,"nome":"Despesas Comerciais","tipo":"S","macro":"OPERACIONAL","codigo":"","children":[{"id":null,"nome":"Anuncios e Comerciais","tipo":"A","macro":"OPERACIONAL","codigo":"","children":[],"pathKey":"M0/8/9/0"},{"id":null,"nome":"Propagandas e insercoes - tv/radio/impressos","tipo":"A","macro":"OPERACIONAL","codigo":"","children":[],"pathKey":"M0/8/9/1"},{"id":256,"nome":"Anuncios e Publicações","tipo":"A","macro":"OPERACIONAL","codigo":"","children":[],"pathKey":"M0/8/9/2"}],"pathKey":"M0/8/9"},{"id":224,"nome":"Despesas Operacionais","tipo":"S","macro":"OPERACIONAL","codigo":"","children":[{"id":191,"nome":"Aluguel de Maquineta de Cartão","tipo":"A","macro":"OPERACIONAL","codigo":"","children":[],"pathKey":"M0/8/10/0"}],"pathKey":"M0/8/10"},{"id":null,"nome":"Relacionamentos","tipo":"S","macro":"OPERACIONAL","codigo":"","children":[{"id":85,"nome":"Brindes","tipo":"A","macro":"OPERACIONAL","codigo":"","children":[],"pathKey":"M0/8/11/0"},{"id":null,"nome":"Eventos Clientes Externos","tipo":"A","macro":"OPERACIONAL","codigo":"","children":[],"pathKey":"M0/8/11/1"},{"id":329,"nome":"Parcerias Comerciais","tipo":"A","macro":"OPERACIONAL","codigo":"","children":[],"pathKey":"M0/8/11/2"}],"pathKey":"M0/8/11"},{"id":null,"nome":"Comissões e Bonificações","tipo":"S","macro":"OPERACIONAL","codigo":"","children":[{"id":23,"nome":"Comissão sobre vendas","tipo":"A","macro":"OPERACIONAL","codigo":"","children":[],"pathKey":"M0/8/12/0"},{"id":null,"nome":"Representantes","tipo":"A","macro":"OPERACIONAL","codigo":"","children":[],"pathKey":"M0/8/12/1"},{"id":null,"nome":"Vendedores Externos","tipo":"A","macro":"OPERACIONAL","codigo":"","children":[],"pathKey":"M0/8/12/2"},{"id":null,"nome":"Televendas","tipo":"A","macro":"OPERACIONAL","codigo":"","children":[],"pathKey":"M0/8/12/3"},{"id":null,"nome":"Bonificação Comercial","tipo":"A","macro":"OPERACIONAL","codigo":"","children":[],"pathKey":"M0/8/12/4"}],"pathKey":"M0/8/12"},{"id":245,"nome":"Serviços de Terceiros","tipo":"S","macro":"OPERACIONAL","codigo":"","children":[{"id":null,"nome":"Judicial","tipo":"S","macro":"OPERACIONAL","codigo":"","children":[{"id":65,"nome":"Assessoria Juridica","tipo":"A","macro":"OPERACIONAL","codigo":"","children":[],"pathKey":"M0/8/13/0/0"},{"id":297,"nome":"Despesas legais e judiciais","tipo":"A","macro":"OPERACIONAL","codigo":"","children":[],"pathKey":"M0/8/13/0/1"}],"pathKey":"M0/8/13/0"},{"id":null,"nome":"Gestão Empresarial","tipo":"S","macro":"OPERACIONAL","codigo":"","children":[{"id":66,"nome":"Assessoria e Consultoria","tipo":"A","macro":"OPERACIONAL","codigo":"","children":[],"pathKey":"M0/8/13/1/0"}],"pathKey":"M0/8/13/1"},{"id":null,"nome":"Marketing/Publicidade","tipo":"S","macro":"OPERACIONAL","codigo":"","children":[{"id":261,"nome":"Assessoria de marketing e publicidade","tipo":"A","macro":"OPERACIONAL","codigo":"","children":[],"pathKey":"M0/8/13/2/0"},{"id":null,"nome":"Propagandas e insercoes-tv/radio/impressos","tipo":"A","macro":"OPERACIONAL","codigo":"","children":[],"pathKey":"M0/8/13/2/1"},{"id":264,"nome":"Material de Marketing e Publicidade","tipo":"A","macro":"OPERACIONAL","codigo":"","children":[],"pathKey":"M0/8/13/2/2"}],"pathKey":"M0/8/13/2"},{"id":null,"nome":"Contabilidades","tipo":"S","macro":"OPERACIONAL","codigo":"","children":[{"id":64,"nome":"Assessoria Contábil","tipo":"A","macro":"OPERACIONAL","codigo":"","children":[],"pathKey":"M0/8/13/3/0"}],"pathKey":"M0/8/13/3"},{"id":null,"nome":"Demais Serviços","tipo":"S","macro":"OPERACIONAL","codigo":"","children":[{"id":360,"nome":"Assistência Técnica","tipo":"A","macro":"OPERACIONAL","codigo":"","children":[],"pathKey":"M0/8/13/4/0"},{"id":100,"nome":"Manutenção de hardware","tipo":"A","macro":"OPERACIONAL","codigo":"","children":[],"pathKey":"M0/8/13/4/1"},{"id":359,"nome":"Coleta de Lixo","tipo":"A","macro":"OPERACIONAL","codigo":"","children":[],"pathKey":"M0/8/13/4/2"},{"id":275,"nome":"Serviços manutenção Eletrico","tipo":"A","macro":"OPERACIONAL","codigo":"","children":[],"pathKey":"M0/8/13/4/3"}],"pathKey":"M0/8/13/4"},{"id":325,"nome":"Distribuição de Lucros","tipo":"S","macro":"OPERACIONAL","codigo":"","children":[{"id":325,"nome":"Distribuição de Lucros","tipo":"A","macro":"OPERACIONAL","codigo":"","children":[],"pathKey":"M0/8/13/5/0"},{"id":null,"nome":"Retirada de Lucros","tipo":"A","macro":"OPERACIONAL","codigo":"","children":[],"pathKey":"M0/8/13/5/1"}],"pathKey":"M0/8/13/5"}],"pathKey":"M0/8/13"}],"pathKey":"M0/8"}],"pathKey":"M0"},{"nome":"Fluxo de Caixa Financeiro","tipo":"S","macro":"FINANCIAMENTOS","codigo":"","children":[{"id":null,"nome":"Receitas Financeiras","tipo":"S","macro":"FINANCIAMENTOS","codigo":"","children":[{"id":124,"nome":"Investimento em aplicações financeiras","tipo":"A","macro":"FINANCIAMENTOS","codigo":"","children":[],"pathKey":"M1/0/0"}],"pathKey":"M1/0"},{"id":318,"nome":"Despesas Financeiras","tipo":"S","macro":"FINANCIAMENTOS","codigo":"","children":[{"id":314,"nome":"Emprestimos e financiamentos - CG - Principal","tipo":"A","macro":"FINANCIAMENTOS","codigo":"","children":[],"pathKey":"M1/1/0"},{"id":321,"nome":"Emprestimos e financiamentos - CG - Juros","tipo":"A","macro":"FINANCIAMENTOS","codigo":"","children":[],"pathKey":"M1/1/1"}],"pathKey":"M1/1"},{"id":null,"nome":"Antecipação","tipo":"S","macro":"FINANCIAMENTOS","codigo":"","children":[{"id":287,"nome":"Antecipacao de recebiveis - taxas e juros","tipo":"A","macro":"FINANCIAMENTOS","codigo":"","children":[],"pathKey":"M1/2/0"}],"pathKey":"M1/2"},{"id":null,"nome":"Taxas e Demais","tipo":"S","macro":"FINANCIAMENTOS","codigo":"","children":[{"id":315,"nome":"Tarifas Bancarias","tipo":"A","macro":"FINANCIAMENTOS","codigo":"","children":[],"pathKey":"M1/3/0"},{"id":316,"nome":"Taxas adm de cartoes","tipo":"A","macro":"FINANCIAMENTOS","codigo":"","children":[],"pathKey":"M1/3/1"},{"id":null,"nome":"Taxas de Administração de Consórcios","tipo":"A","macro":"FINANCIAMENTOS","codigo":"","children":[],"pathKey":"M1/3/2"},{"id":344,"nome":"IOF","tipo":"A","macro":"FINANCIAMENTOS","codigo":"","children":[],"pathKey":"M1/3/3"},{"id":234,"nome":"Juros auferidos","tipo":"A","macro":"FINANCIAMENTOS","codigo":"","children":[],"pathKey":"M1/3/4"},{"id":107,"nome":"Juros de conta garantida","tipo":"A","macro":"FINANCIAMENTOS","codigo":"","children":[],"pathKey":"M1/3/5"},{"id":null,"nome":"Juros sobre parcelamento tributário","tipo":"A","macro":"FINANCIAMENTOS","codigo":"","children":[],"pathKey":"M1/3/6"},{"id":286,"nome":"Juros sobre atrasos de pagamentos","tipo":"A","macro":"FINANCIAMENTOS","codigo":"","children":[],"pathKey":"M1/3/7"}],"pathKey":"M1/3"}],"pathKey":"M1"},{"nome":"Fluxo de Caixa Investimentos","tipo":"S","macro":"INVESTIMENTOS","codigo":"","children":[{"id":null,"nome":"Receitas Provenientes de Investimentos","tipo":"S","macro":"INVESTIMENTOS","codigo":"","children":[{"id":null,"nome":"Investimentos","tipo":"S","macro":"INVESTIMENTOS","codigo":"","children":[{"id":299,"nome":"Imobilizado","tipo":"A","macro":"INVESTIMENTOS","codigo":"","children":[],"pathKey":"M2/0/0/0"},{"id":288,"nome":"Obras na estrutura","tipo":"A","macro":"INVESTIMENTOS","codigo":"","children":[],"pathKey":"M2/0/0/1"}],"pathKey":"M2/0/0"}],"pathKey":"M2/0"}],"pathKey":"M2"}]}